{
  "date": "2026-07-17",
  "weekday": 4,
  "_generator": "google_posts_today_cloud.py",
  "weekday_name": "금",
  "publish": "true",
  "week": "2026-W29",
  "lang": "ko",
  "lang_label": "한국어",
  "body": "맑은 하늘 청명 시즌, 아이부터 어르신까지 온 가족이 함께 즐길 수 있는 특별한 제주 럭셔리 투어를 찾으신다면, 그랑블루요트 선셋 크루즈가 완벽한 선택입니다. 한국 유일의 공인 카타마란 쌍동선으로 흔들림 없이 안정적인 60분 항해를 즐겨보세요.\n\n· 넓은 갑판 위에서 우리 가족만의 프라이빗한 공간을 누릴 수 있습니다. 눈부신 제주 노을 아래에서 소중한 사람들과 잊지 못할 추억을 만들어 보세요.\n· 시원한 생맥주, 와인, 제주 감귤 주스는 물론, 제주 로컬 스낵과 따끈한 라면까지 무제한으로 즐기며 바다 위에서 즐기는 특별한 가족 식사를 경험할 수 있습니다.\n· 서귀포 대포항에서 출발하여 월평 주상절리와 코끼리 바위 등 제주 남쪽 바다의 아름다운 비경을 감상하고, 황홀한 제주 노을을 배경으로 인생 사진을 남길 수 있습니다.\n\n환상적인 제주 가족여행의 하이라이트를 그랑블루요트와 함께하세요.\n\n예약은 컨시어지 -> 보딩 -> 출발 순서로 진행됩니다.\n\n예약하기 → https://www.klook.com/en-US/activity/170600-jeju-grandebleu-sunset-yacht-experience/?utm_source=google_posts&utm_medium=cta&utm_campaign=jeju_yacht",
  "body_length": 633,
  "photo_url": "https://raw.githubusercontent.com/jm7397776-byte/grandebleu-photos/main/yacht_434_interior_lounge.jpg",
  "seo_keywords": "제주 럭셔리 투어, 제주 가족여행, 제주 노을, 제주 와인 크루즈",
  "cta_action_type": "BOOK",
  "cta_url": "https://www.klook.com/en-US/activity/170600-jeju-grandebleu-sunset-yacht-experience/?utm_source=google_posts&utm_medium=cta&utm_campaign=jeju_yacht",
  "_make_com_hint": "HTTP module → JSON parse → GBP Create Post (photo_url=media, body=summary, cta_action_type+cta_url)"
}